sgb_ftso_contracts/__init__.py
sgb_ftso_contracts/factories.py
sgb_ftso_contracts-0.1.1.dist-info/METADATA
sgb_ftso_contracts-0.1.1.dist-info/WHEEL
sgb_ftso_contracts-0.1.1.dist-info/top_level.txt
sgb_ftso_contracts-0.1.1.dist-info/RECORD
