Metadata-Version: 2.1
Name: sgb-ftso-contracts
Version: 0.1.1
Summary: Songbird network FTSO contract factory library
Home-page: https://sgb-ftso-contracts.readthedocs.io/
Author: Chuck Benedict
Author-email: itsme@chuckstechtalk.com
License: MIT
Classifier: Intended Audience :: Developers
Classifier: License :: OSI Approved :: MIT License
Classifier: Programming Language :: Python
Classifier: Programming Language :: Python :: 3
Classifier: Programming Language :: Python :: 3.6
Classifier: Programming Language :: Python :: 3.7
Classifier: Programming Language :: Python :: 3.8
Classifier: Programming Language :: Python :: 3.9
Classifier: Operating System :: OS Independent
Requires-Dist: web3
Requires-Dist: requests
